nanaraTest/test1.py
nanaraTest/test2.py
nanaraTest-0.0.0.2.dist-info/METADATA
nanaraTest-0.0.0.2.dist-info/WHEEL
nanaraTest-0.0.0.2.dist-info/top_level.txt
nanaraTest-0.0.0.2.dist-info/RECORD
