Metadata-Version: 2.1
Name: nanaraTest
Version: 0.0.0.2
Summary: My Frist Test Package
Home-page: https://www.naver.com
Author: Youngbum Gim
Author-email: znslek@gmail.com
License: MIT
Platform: UNKNOWN
Requires-Python: >=3
